LICENSE.txt
MANIFEST.in
README.rst
setup.py
TheanoLM.egg-info/PKG-INFO
TheanoLM.egg-info/SOURCES.txt
TheanoLM.egg-info/dependency_links.txt
TheanoLM.egg-info/requires.txt
TheanoLM.egg-info/top_level.txt
bin/theanolm
bin/wctool
docs/about.rst
docs/api.rst
docs/applying.rst
docs/calling.rst
docs/contributing.rst
docs/index.rst
docs/installation.rst
docs/training.rst
docs/usage.rst
docs/images/batch-processing.png
kaldi/steps/lmrescore_theanolm.sh
kaldi/steps/lmrescore_theanolm_nbest.sh
kaldi/steps/score_sclite.sh
kaldi/utils/theanolm_compute_scores.sh
tests/theanolm/__init__.py
tests/theanolm/basiclayer_test.py
tests/theanolm/classdistribution_test.py
tests/theanolm/iterators_test.py
tests/theanolm/lattice_test.py
tests/theanolm/latticedecoder_test.py
tests/theanolm/operations_test.py
tests/theanolm/probfunctions_test.py
tests/theanolm/recurrentstate_test.py
tests/theanolm/score_test.py
tests/theanolm/statistics_test.py
tests/theanolm/textsampler_test.py
tests/theanolm/textscorer_test.py
tests/theanolm/trainers_test.py
tests/theanolm/vocabulary_test.py
tests/theanolm/wordclass_test.py
tests/wordclasses/__init__.py
tests/wordclasses/bigramoptimizer_test.py
theanolm/__init__.py
theanolm/textsampler.py
theanolm/version.py
theanolm/architectures/lstm1500.arch
theanolm/architectures/lstm300.arch
theanolm/backend/__init__.py
theanolm/backend/classdistribution.py
theanolm/backend/debugfunctions.py
theanolm/backend/exceptions.py
theanolm/backend/filetypes.py
theanolm/backend/gpu.py
theanolm/backend/matrixfunctions.py
theanolm/backend/operations.py
theanolm/backend/parameters.py
theanolm/backend/probfunctions.py
theanolm/commands/__init__.py
theanolm/commands/decode.py
theanolm/commands/sample.py
theanolm/commands/score.py
theanolm/commands/train.py
theanolm/commands/version.py
theanolm/network/__init__.py
theanolm/network/additionlayer.py
theanolm/network/architecture.py
theanolm/network/basiclayer.py
theanolm/network/bidirectionallayer.py
theanolm/network/dropoutlayer.py
theanolm/network/fullyconnectedlayer.py
theanolm/network/glulayer.py
theanolm/network/grulayer.py
theanolm/network/highwaylayer.py
